build/lib/build/lib/build/lib/build/lib/data/__init__.py
build/lib/build/lib/build/lib/build/lib/hairloom/__init__.py
build/lib/build/lib/build/lib/build/lib/hairloom/bundle.py
build/lib/build/lib/build/lib/build/lib/hairloom/cli.py
build/lib/build/lib/build/lib/build/lib/hairloom/collect.py
build/lib/build/lib/build/lib/build/lib/hairloom/datatypes.py
build/lib/build/lib/build/lib/build/lib/hairloom/utils.py
build/lib/build/lib/build/lib/data/__init__.py
build/lib/build/lib/build/lib/docs/conf.py
build/lib/build/lib/build/lib/hairloom/__init__.py
build/lib/build/lib/build/lib/hairloom/bundle.py
build/lib/build/lib/build/lib/hairloom/cli.py
build/lib/build/lib/build/lib/hairloom/collect.py
build/lib/build/lib/build/lib/hairloom/datatypes.py
build/lib/build/lib/build/lib/hairloom/utils.py
build/lib/build/lib/build/lib/hairloom/data/__init__.py
build/lib/build/lib/build/lib/tests/test_cli.py
build/lib/build/lib/build/lib/tests/test_collect.py
build/lib/build/lib/build/lib/tests/test_datatypes.py
build/lib/build/lib/build/lib/tests/test_utils.py
build/lib/build/lib/build/lib/tests/scripts/make_test_data.py
build/lib/build/lib/data/__init__.py
build/lib/build/lib/docs/conf.py
build/lib/build/lib/hairloom/__init__.py
build/lib/build/lib/hairloom/bundle.py
build/lib/build/lib/hairloom/cli.py
build/lib/build/lib/hairloom/collect.py
build/lib/build/lib/hairloom/datatypes.py
build/lib/build/lib/hairloom/utils.py
build/lib/build/lib/hairloom/data/__init__.py
build/lib/build/lib/tests/test_cli.py
build/lib/build/lib/tests/test_collect.py
build/lib/build/lib/tests/test_datatypes.py
build/lib/build/lib/tests/test_utils.py
build/lib/build/lib/tests/scripts/make_test_data.py
build/lib/data/__init__.py
build/lib/docs/conf.py
build/lib/hairloom/__init__.py
build/lib/hairloom/bundle.py
build/lib/hairloom/cli.py
build/lib/hairloom/collect.py
build/lib/hairloom/datatypes.py
build/lib/hairloom/utils.py
build/lib/hairloom/data/__init__.py
build/lib/tests/test_cli.py
hairloom-0.1.2.dist-info/LICENSE
hairloom-0.1.2.dist-info/METADATA
hairloom-0.1.2.dist-info/WHEEL
hairloom-0.1.2.dist-info/entry_points.txt
hairloom-0.1.2.dist-info/top_level.txt
hairloom-0.1.2.dist-info/RECORD
