Metadata-Version: 2.1
Name: hairloom
Version: 0.1.2
Summary: A package to analyze split reads of long read data
Author-email: Seongmin Choi <soymintc@gmail.com>
Project-URL: Homepage, https://github.com/shahcompbio/hairloom
Project-URL: Documentation, https://readthedocs.org/projects/hairloom
Project-URL: Issues, https://github.com/shahcompbio/hairloom/issues
Classifier: Programming Language :: Python :: 3
Classifier: License :: OSI Approved :: MIT License
Classifier: Operating System :: OS Independent
Requires-Python: >=3.9
License-File: LICENSE
Provides-Extra: dev
Requires-Dist: pytest ; extra == 'dev'
Requires-Dist: pytest-cov ; extra == 'dev'
